llama_index/readers/mangadex/__init__.py
llama_index/readers/mangadex/base.py
llama_index_readers_mangadex-0.4.1.dist-info/METADATA
llama_index_readers_mangadex-0.4.1.dist-info/WHEEL
llama_index_readers_mangadex-0.4.1.dist-info/licenses/LICENSE
llama_index_readers_mangadex-0.4.1.dist-info/RECORD
